batch_automation/__init__.py
batch_automation/davinci/DaVinci.py
batch_automation/davinci/Folder.py
batch_automation/davinci/Gallery.py
batch_automation/davinci/GalleryStillAlbum.py
batch_automation/davinci/MediaPool.py
batch_automation/davinci/MediaPoolItem.py
batch_automation/davinci/MediaStorage.py
batch_automation/davinci/Project.py
batch_automation/davinci/ProjectManager.py
batch_automation/davinci/Timeline.py
batch_automation/davinci/TimelineItem.py
batch_automation/davinci/__init__.py
batch_automation/deadline/__init__.py
batch_automation/deadline/api/Balancer.py
batch_automation/deadline/api/ConnectionProperty.py
batch_automation/deadline/api/DeadlineConnect.py
batch_automation/deadline/api/DeadlineSend.py
batch_automation/deadline/api/DeadlineUtility.py
batch_automation/deadline/api/Groups.py
batch_automation/deadline/api/JobReports.py
batch_automation/deadline/api/JobTaskLimit.py
batch_automation/deadline/api/Jobs.py
batch_automation/deadline/api/Limits.py
batch_automation/deadline/api/MappedPaths.py
batch_automation/deadline/api/MaximumPriority.py
batch_automation/deadline/api/Plugins.py
batch_automation/deadline/api/Pools.py
batch_automation/deadline/api/ProxyServer.py
batch_automation/deadline/api/Pulse.py
batch_automation/deadline/api/Repository.py
batch_automation/deadline/api/Slaves.py
batch_automation/deadline/api/SlavesRenderingJob.py
batch_automation/deadline/api/TaskReports.py
batch_automation/deadline/api/Tasks.py
batch_automation/deadline/api/Users.py
batch_automation/deadline/api/__init__.py
batch_automation/deadline/custom/__init__.py
batch_automation/deadline/custom/custom.py
batch_automation/google/__init__.py
batch_automation/google/api.py
batch_automation/mongodb/__init__.py
batch_automation/mongodb/mongo.py
batch_automation/tools/__init__.py
batch_automation/tools/helpers.py
batch_automation/tools/read_config.py
batch_automation-0.0.3.dist-info/LICENSE
batch_automation-0.0.3.dist-info/METADATA
batch_automation-0.0.3.dist-info/WHEEL
batch_automation-0.0.3.dist-info/top_level.txt
batch_automation-0.0.3.dist-info/RECORD
