Metadata-Version: 2.1
Name: batch-automation
Version: 0.0.3
Summary: Batch Automation Tools and Packages
Home-page: https://github.com/GMarinow/batch_automation
Author: Georgi Marinov
Author-email: georgi.marinow@gmail.com
License: Apache Software License 2.0
Project-URL: Bug Tracker, https://github.com/GMarinow/batch_automation/issues
Platform: UNKNOWN
Classifier: License :: OSI Approved :: Apache Software License
Classifier: Operating System :: OS Independent
Classifier: Programming Language :: Python :: 3
Classifier: Programming Language :: Python :: 3.6
Requires-Python: >=3.6
License-File: LICENSE
Requires-Dist: google-api-python-client
Requires-Dist: google-auth-httplib2
Requires-Dist: google-auth-oauthlib
Requires-Dist: google
Requires-Dist: pymongo (==3.6)
Requires-Dist: dnspython
Requires-Dist: PyYAML
